hackmud_chat/__init__.py
hackmud_chat/hackmud.py
hackmud_chat/hackmud_chat.py
hackmud_chat-0.1a4.dist-info/LICENSE
hackmud_chat-0.1a4.dist-info/METADATA
hackmud_chat-0.1a4.dist-info/WHEEL
hackmud_chat-0.1a4.dist-info/top_level.txt
hackmud_chat-0.1a4.dist-info/RECORD
