Metadata-Version: 2.1
Name: hackmud-chat
Version: 0.1a4
Summary: Python binding to Hackmud's chat API
Home-page: https://github.com/chalios/hackmud_chat_py
Author: Chalios
Author-email: chalios@protonmail.com
License: MIT
Keywords: hackmud chat api
Platform: UNKNOWN
Classifier: Development Status :: 3 - Alpha
Classifier: License :: OSI Approved :: MIT License
Classifier: Programming Language :: Python :: 2.7
Classifier: Topic :: Communications :: Chat
Classifier: Topic :: Games/Entertainment :: Multi-User Dungeons (MUD)
Requires-Dist: requests
